htcdaskgateway/__init__.py
htcdaskgateway/cluster.py
htcdaskgateway/gateway.py
htcdaskgateway/options.py
htcdaskgateway/untitled.py
htcdaskgateway-0.1.24.dist-info/METADATA
htcdaskgateway-0.1.24.dist-info/WHEEL
htcdaskgateway-0.1.24.dist-info/top_level.txt
htcdaskgateway-0.1.24.dist-info/RECORD
